capnp/__init__.pxd
capnp/__init__.py
capnp/_gen.py
capnp/c++.capnp
capnp/schema.capnp
capnp/version.py
capnp/helpers/__init__.pxd
capnp/helpers/asyncHelper.h
capnp/helpers/capabilityHelper.h
capnp/helpers/checkCompiler.h
capnp/helpers/fixMaybe.h
capnp/helpers/helpers.pxd
capnp/helpers/non_circular.pxd
capnp/helpers/rpcHelper.h
capnp/helpers/serialize.h
capnp/includes/__init__.pxd
capnp/includes/capnp_cpp.pxd
capnp/includes/schema_cpp.pxd
capnp/includes/types.pxd
capnp/lib/__init__.pxd
capnp/lib/__init__.py
capnp/lib/capnp-rpc.dll
capnp/lib/capnp.cp37-win_amd64.pyd
capnp/lib/capnp.dll
capnp/lib/capnp.pxd
capnp/lib/capnp.pyx
capnp/lib/capnpc.dll
capnp/lib/kj-async.dll
capnp/lib/kj.dll
capnp/lib/pickle_helper.py
capnp/templates/module.pyx
capnp/templates/setup.py.tmpl
pycapnp_for_win_zalf_rpm-0.7.0.dist-info/LICENSE
pycapnp_for_win_zalf_rpm-0.7.0.dist-info/METADATA
pycapnp_for_win_zalf_rpm-0.7.0.dist-info/WHEEL
pycapnp_for_win_zalf_rpm-0.7.0.dist-info/entry_points.txt
pycapnp_for_win_zalf_rpm-0.7.0.dist-info/top_level.txt
pycapnp_for_win_zalf_rpm-0.7.0.dist-info/RECORD
